jdAnimatedImageEditor/AboutDialog.py
jdAnimatedImageEditor/Environment.py
jdAnimatedImageEditor/FFmpegHandler.py
jdAnimatedImageEditor/Functions.py
jdAnimatedImageEditor/Icon.svg
jdAnimatedImageEditor/Languages.py
jdAnimatedImageEditor/MainWindow.py
jdAnimatedImageEditor/Settings.py
jdAnimatedImageEditor/SettingsDialog.py
jdAnimatedImageEditor/__init__.py
jdAnimatedImageEditor/version.txt
jdAnimatedImageEditor/translations/jdAnimatedImageEditor_de.qm
jdAnimatedImageEditor/translations/jdAnimatedImageEditor_nl.qm
jdAnimatedImageEditor/translations/jdAnimatedImageEditor_sv.qm
jdAnimatedImageEditor/ui_compiled/AboutDialog.py
jdAnimatedImageEditor/ui_compiled/MainWindow.py
jdAnimatedImageEditor/ui_compiled/SettingsDialog.py
jdAnimatedImageEditor/ui_compiled/__init__.py
jdAnimatedImageEditor-1.4.dist-info/LICENSE
jdAnimatedImageEditor-1.4.dist-info/METADATA
jdAnimatedImageEditor-1.4.dist-info/WHEEL
jdAnimatedImageEditor-1.4.dist-info/entry_points.txt
jdAnimatedImageEditor-1.4.dist-info/top_level.txt
jdAnimatedImageEditor-1.4.dist-info/RECORD
